sphinx_ros/__init__.py
sphinx_ros/directives.py
sphinx_ros/domain.py
sphinx_ros/indices.py
sphinx_ros/xref_role.py
sphinx_ros-0.1.0.dist-info/LICENSE
sphinx_ros-0.1.0.dist-info/METADATA
sphinx_ros-0.1.0.dist-info/WHEEL
sphinx_ros-0.1.0.dist-info/top_level.txt
sphinx_ros-0.1.0.dist-info/RECORD
