Metadata-Version: 2.1
Name: sphinx-ros
Version: 0.1.0
Summary: Sphinx extension to document ROS packages.
Home-page: http://sphinx-ros.readthedocs.io/
Author: M.J.W. Snippe
Author-email: maxsnippe@gmail.com
License: MIT
Project-URL: Issue tracker, https://github.com/max-sn/sphinx_ros/issues
Project-URL: Documentation, http://sphinx-ros.readthedocs.io/
Project-URL: Repository, https://github.com/max-sn/sphinx_ros/
Platform: linux
Classifier: Development Status :: 4 - Beta
Classifier: Environment :: Console
Classifier: Environment :: Web Environment
Classifier: Intended Audience :: Developers
Classifier: License :: OSI Approved :: MIT License
Classifier: Operating System :: OS Independent
Classifier: Programming Language :: Python
Classifier: Topic :: Documentation
Classifier: Topic :: Utilities
Requires-Dist: Sphinx (>=1.8)
Requires-Dist: setuptools (>=20.7)
Requires-Dist: rospkg
